odoo/addons/stock_lot_scrap/README.rst
odoo/addons/stock_lot_scrap/__init__.py
odoo/addons/stock_lot_scrap/__manifest__.py
odoo/addons/stock_lot_scrap/i18n/de.po
odoo/addons/stock_lot_scrap/i18n/es.po
odoo/addons/stock_lot_scrap/i18n/fr.po
odoo/addons/stock_lot_scrap/i18n/hr.po
odoo/addons/stock_lot_scrap/i18n/it.po
odoo/addons/stock_lot_scrap/i18n/pt.po
odoo/addons/stock_lot_scrap/i18n/pt_BR.po
odoo/addons/stock_lot_scrap/i18n/sl.po
odoo/addons/stock_lot_scrap/i18n/stock_lot_scrap.pot
odoo/addons/stock_lot_scrap/models/__init__.py
odoo/addons/stock_lot_scrap/models/stock_production_lot.py
odoo/addons/stock_lot_scrap/models/stock_scrap.py
odoo/addons/stock_lot_scrap/readme/CONFIGURE.rst
odoo/addons/stock_lot_scrap/readme/CONTRIBUTORS.rst
odoo/addons/stock_lot_scrap/readme/DESCRIPTION.rst
odoo/addons/stock_lot_scrap/readme/USAGE.rst
odoo/addons/stock_lot_scrap/static/description/icon.png
odoo/addons/stock_lot_scrap/static/description/index.html
odoo/addons/stock_lot_scrap/tests/__init__.py
odoo/addons/stock_lot_scrap/tests/test_stock_lot_scrap.py
odoo14_addon_stock_lot_scrap-14.0.1.0.2.dist-info/METADATA
odoo14_addon_stock_lot_scrap-14.0.1.0.2.dist-info/WHEEL
odoo14_addon_stock_lot_scrap-14.0.1.0.2.dist-info/top_level.txt
odoo14_addon_stock_lot_scrap-14.0.1.0.2.dist-info/RECORD
